fastbulma/__init__.py
fastbulma/__main__.py
fastbulma/cli.py
fastbulma/static/css/fastbulma.css
fastbulma/static/js/fastbulma.js
fastbulma-0.3.0.dist-info/licenses/LICENSE
fastbulma-0.3.0.dist-info/METADATA
fastbulma-0.3.0.dist-info/WHEEL
fastbulma-0.3.0.dist-info/entry_points.txt
fastbulma-0.3.0.dist-info/top_level.txt
fastbulma-0.3.0.dist-info/RECORD
