Metadata-Version: 2.4
Name: fastbulma
Version: 0.3.0
Summary: FastBulma framework: Combining Bulma CSS utilities with FAST web components
Author-email: FastBulma Team <team@fastbulma.dev>
License: BSD-3-Clause
Keywords: css,framework,components,web,frontend,bulma,fast,microsoft,web-components
Classifier: Development Status :: 4 - Beta
Classifier: Environment :: Web Environment
Classifier: Intended Audience :: Developers
Classifier: License :: OSI Approved :: BSD License
Classifier: Operating System :: OS Independent
Classifier: Programming Language :: Python :: 3
Classifier: Programming Language :: Python :: 3.13
Classifier: Topic :: Software Development :: Libraries :: Python Modules
Classifier: Topic :: Internet :: WWW/HTTP :: Dynamic Content
Classifier: Topic :: Software Development :: User Interfaces
Requires-Python: >=3.13
License-File: LICENSE
Provides-Extra: dev
Requires-Dist: crackerjack>=0.1.0; extra == "dev"
Requires-Dist: session-buddy>=0.1.0; extra == "dev"
Requires-Dist: ruff>=0.8.0; extra == "dev"
Requires-Dist: pytest>=8.0.0; extra == "dev"
Requires-Dist: pytest-cov>=6.0.0; extra == "dev"
Requires-Dist: pytest-xdist>=3.6.0; extra == "dev"
Requires-Dist: pyright>=1.1.300; extra == "dev"
Requires-Dist: bandit[toml]>=1.7.10; extra == "dev"
Requires-Dist: creosote>=3.0.0; extra == "dev"
Requires-Dist: codespell>=2.3.0; extra == "dev"
Requires-Dist: refurb>=2.0.0; extra == "dev"
Requires-Dist: complexipy>=0.9.0; extra == "dev"
Dynamic: license-file
